linear_python/__init__.py
linear_python/base.py
linear_python/client.py
linear_python/config.py
linear_python/resources/__init__.py
linear_python/resources/issues.py
linear_python/resources/projects.py
linear_python/resources/teams.py
linear_python/resources/users.py
linear_python/types/__init__.py
linear_python/types/issue.py
linear_python/types/project.py
linear_python/types/team.py
linear_python/types/user.py
tests/__init__.py
tests/test_base.py
tests/test_issues.py
tests/test_projects.py
tests/test_teams.py
tests/test_users.py
linear_python-0.2.2.dist-info/LICENSE
linear_python-0.2.2.dist-info/METADATA
linear_python-0.2.2.dist-info/WHEEL
linear_python-0.2.2.dist-info/top_level.txt
linear_python-0.2.2.dist-info/RECORD
