Metadata-Version: 2.1
Name: linear-python
Version: 0.2.2
Summary: A Python client for the Linear API
Home-page: https://github.com/jpbullalayao/linear-python
Author: Jourdan Bul-lalayao
Classifier: Programming Language :: Python :: 3
Classifier: License :: OSI Approved :: MIT License
Classifier: Operating System :: OS Independent
Requires-Python: >=3.7
License-File: LICENSE
Requires-Dist: requests>=2.31.0
Requires-Dist: python-dotenv>=1.0.0
Requires-Dist: strawberry-graphql>=0.138.0
Requires-Dist: pydantic>=2.0.0
Requires-Dist: typing-extensions>=4.5.0
